{
	"data": [
		{
			"address": "bandvaloper1f6htx23e4xfu0dkpa2ck2kk63la2ej947cq0w4",
			"moniker": "Kruskal",
			"website": "",
			"token": 8908945381810,
			"commission": 1,
			"votingPower": 0.097247,
			"rank": 1,
			"jailed": false,
			"participation": 54.54545454545454,
			"windowMissCount": 96.7,
			"commissionScore": 100,
			"totalScore": 83.74848484848485,
			"level": 4
		},
		{
			"address": "bandvaloper1wja9nds8klxcjurvxerdsun4t52zfjvqpj6y54",
			"moniker": "Knuth",
			"website": "",
			"token": 8895567771721,
			"commission": 1,
			"votingPower": 0.097101,
			"rank": 2,
			"jailed": false,
			"participation": 63.63636363636363,
			"windowMissCount": 97.7,
			"commissionScore": 100,
			"totalScore": 87.11212121212122,
			"level": 4
		},
		{
			"address": "bandvaloper1r00x80djyu6wkxpceegmvn5w9nx65prgqhxkzq",
			"moniker": "Dijkstra",
			"website": "",
			"token": 8748077339589,
			"commission": 1,
			"votingPower": 0.095491,
			"rank": 3,
			"jailed": false,
			"participation": 72.72727272727273,
			"windowMissCount": 47.4,
			"commissionScore": 100,
			"totalScore": 73.37575757575758,
			"level": 4
		},
		{
			"address": "bandvaloper128dkddh98pfwdxg07t36fxedczthg0p2mdcs42",
			"moniker": "Hamming",
			"website": "",
			"token": 8502283032154,
			"commission": 1,
			"votingPower": 0.092808,
			"rank": 4,
			"jailed": false,
			"participation": 72.72727272727273,
			"windowMissCount": 96.1,
			"commissionScore": 100,
			"totalScore": 89.60909090909091,
			"level": 4
		},
		{
			"address": "bandvaloper1m88fha4982ev7smptzu8a7wvt8wkxdvfewh2md",
			"moniker": "Tarjan",
			"website": "",
			"token": 8415248854530,
			"commission": 1,
			"votingPower": 0.091858,
			"rank": 5,
			"jailed": false,
			"participation": 72.72727272727273,
			"windowMissCount": 94.1,
			"commissionScore": 100,
			"totalScore": 88.94242424242424,
			"level": 4
		},
		{
			"address": "bandvaloper153znf8a89gmunexzrg2ud2yz47gyer9c05t2l8",
			"moniker": "Binance validator",
			"website": "",
			"token": 6683311968017,
			"commission": 0.025,
			"votingPower": 0.072952,
			"rank": 6,
			"jailed": false,
			"participation": 0.0,
			"windowMissCount": 70.1,
			"commissionScore": 12.5,
			"totalScore": 27.53333333333333,
			"level": 1
		},
		{
			"address": "bandvaloper17d3uhcjlh4jyqcep82jfsrg8avsngklxxan5tg",
			"moniker": "Cosmostation",
			"website": "https://www.cosmostation.io",
			"token": 3926467440997,
			"commission": 0.12,
			"votingPower": 0.04286,
			"rank": 7,
			"jailed": false,
			"participation": 72.72727272727273,
			"windowMissCount": 90.0,
			"commissionScore": 60.0,
			"totalScore": 74.24242424242425,
			"level": 4
		},
		{
			"address": "bandvaloper1zm5p8gg3ugjcdwz9yrxaf6fdptxa4gw04rplr9",
			"moniker": "figment",
			"website": "https://figment.network",
			"token": 3535823961804,
			"commission": 0.1,
			"votingPower": 0.038596,
			"rank": 8,
			"jailed": false,
			"participation": 9.090909090909093,
			"windowMissCount": 70.7,
			"commissionScore": 50.0,
			"totalScore": 43.26363636363637,
			"level": 2
		},
		{
			"address": "bandvaloper1ycs4g7xu8wmf7n4vwwtfsvhtfm7tekvwk34rxz",
			"moniker": "sorawit",
			"website": "https://twitter.com/nomorebear",
			"token": 3031616102164,
			"commission": 0.1,
			"votingPower": 0.033092,
			"rank": 9,
			"jailed": false,
			"participation": 54.54545454545454,
			"windowMissCount": 92.1,
			"commissionScore": 50.0,
			"totalScore": 65.54848484848485,
			"level": 3
		},
		{
			"address": "bandvaloper15urq2dtp9qce4fyc85m6upwm9xul3049fz627w",
			"moniker": "Chorus One",
			"website": "https://chorus.one",
			"token": 2626428406637,
			"commission": 0.12,
			"votingPower": 0.028669,
			"rank": 10,
			"jailed": false,
			"participation": 45.45454545454546,
			"windowMissCount": 78.1,
			"commissionScore": 60.0,
			"totalScore": 61.18484848484849,
			"level": 3
		},
		{
			"address": "bandvaloper1c9ye54e3pzwm3e0zpdlel6pnavrj9qqvn4hl7n",
			"moniker": "StakeWith.Us",
			"website": "https://StakeWith.Us",
			"token": 2583011601881,
			"commission": 0.1,
			"votingPower": 0.028195,
			"rank": 11,
			"jailed": false,
			"participation": 72.72727272727273,
			"windowMissCount": 83.6,
			"commissionScore": 50.0,
			"totalScore": 68.77575757575757,
			"level": 3
		},
		{
			"address": "bandvaloper1q894x7p4ugl3q5l47e8ksll5k5lmx74fxqez5y",
			"moniker": "B-Harvest",
			"website": "",
			"token": 2578438918042,
			"commission": 0.1,
			"votingPower": 0.028145,
			"rank": 12,
			"jailed": false,
			"participation": 63.63636363636363,
			"windowMissCount": 86.3,
			"commissionScore": 50.0,
			"totalScore": 66.64545454545454,
			"level": 3
		},
		{
			"address": "bandvaloper1nqmeykpnqdccxf2kfqnwszy748ll3qlzu0heyt",
			"moniker": "Active Nodes",
			"website": "https://www.activenodes.io",
			"token": 2060998189309,
			"commission": 0.069,
			"votingPower": 0.022497,
			"rank": 13,
			"jailed": false,
			"participation": 72.72727272727273,
			"windowMissCount": 94.4,
			"commissionScore": 34.5,
			"totalScore": 67.2090909090909,
			"level": 3
		},
		{
			"address": "bandvaloper14kn0kk33szpwus9nh8n87fjel8djx0y0wz502z",
			"moniker": "Forbole",
			"website": "https://www.forbole.com/cosmos-hub-validator/",
			"token": 2018110286913,
			"commission": 0.12,
			"votingPower": 0.022029,
			"rank": 14,
			"jailed": false,
			"participation": 72.72727272727273,
			"windowMissCount": 99.0,
			"commissionScore": 60.0,
			"totalScore": 77.24242424242425,
			"level": 4
		},
		{
			"address": "bandvaloper1vvevlfz7r9xrj9kghhguw8ygwvv9x3duldlw3j",
			"moniker": "Pickle Banddd (\ud83c\udd51))",
			"website": "",
			"token": 1594016995000,
			"commission": 0.1,
			"votingPower": 0.0174,
			"rank": 15,
			"jailed": false,
			"participation": 18.181818181818176,
			"windowMissCount": 0,
			"commissionScore": 50.0,
			"totalScore": 22.727272727272723,
			"level": 1
		},
		{
			"address": "bandvaloper1lksevk5362eterq75haf7wxx6jdpgdzyd9ms9h",
			"moniker": "Wanchain",
			"website": "https://www.wanchain.org/",
			"token": 1517923745632,
			"commission": 0.1,
			"votingPower": 0.016569,
			"rank": 16,
			"jailed": false,
			"participation": 0.0,
			"windowMissCount": 85.3,
			"commissionScore": 50.0,
			"totalScore": 45.1,
			"level": 2
		},
		{
			"address": "bandvaloper1dr64r506ln5n3aqqgkccf56uwdd9d9jvlh9l4p",
			"moniker": "HashQuark",
			"website": "https://www.hashquark.io",
			"token": 1504949716103,
			"commission": 0.1,
			"votingPower": 0.016427,
			"rank": 17,
			"jailed": false,
			"participation": 45.45454545454546,
			"windowMissCount": 69.9,
			"commissionScore": 50.0,
			"totalScore": 55.118181818181824,
			"level": 3
		},
		{
			"address": "bandvaloper1nguv0kdayw7qhy6d354el4f87d67ynt52wrdk3",
			"moniker": "Atomic Nodes",
			"website": "https://atomicwallet.io/",
			"token": 1476844444938,
			"commission": 0.1,
			"votingPower": 0.016121,
			"rank": 18,
			"jailed": false,
			"participation": 0.0,
			"windowMissCount": 84.2,
			"commissionScore": 50.0,
			"totalScore": 44.73333333333333,
			"level": 2
		},
		{
			"address": "bandvaloper1cuc594q8uam3rx90tztgplssnymlqnr5epmsjq",
			"moniker": "Wellstake",
			"website": "",
			"token": 1100111752716,
			"commission": 0.1,
			"votingPower": 0.012008,
			"rank": 19,
			"jailed": false,
			"participation": 27.27272727272727,
			"windowMissCount": 86.7,
			"commissionScore": 50.0,
			"totalScore": 54.657575757575756,
			"level": 3
		},
		{
			"address": "bandvaloper14wuzcsyttmyedc7e7z7e0exhg8k94x6eulj6pt",
			"moniker": "Ubik Capital",
			"website": "https://www.ubik.capital",
			"token": 1031052837170,
			"commission": 0.1189,
			"votingPower": 0.011255,
			"rank": 20,
			"jailed": false,
			"participation": 72.72727272727273,
			"windowMissCount": 91.1,
			"commissionScore": 59.45,
			"totalScore": 74.42575757575757,
			"level": 4
		},
		{
			"address": "bandvaloper1qgvcttnjx3enjqg9pnhclt6d4z7qdknavg4q9c",
			"moniker": "WeStaking",
			"website": "https://westaking.io",
			"token": 1019398572524,
			"commission": 0.1,
			"votingPower": 0.011127,
			"rank": 21,
			"jailed": false,
			"participation": 72.72727272727273,
			"windowMissCount": 80.8,
			"commissionScore": 50.0,
			"totalScore": 67.84242424242424,
			"level": 3
		},
		{
			"address": "bandvaloper1948raua2qwgn6rcstgdtk4wyg2zypc2680lej7",
			"moniker": "Injective Labs",
			"website": "injectivelabs.org",
			"token": 1009951666445,
			"commission": 0.1,
			"votingPower": 0.011024,
			"rank": 22,
			"jailed": false,
			"participation": 9.090909090909093,
			"windowMissCount": 99.7,
			"commissionScore": 50.0,
			"totalScore": 52.93030303030304,
			"level": 3
		},
		{
			"address": "bandvaloper1v7teuxaulwukplu90f0ra60vs2xpqystg89g95",
			"moniker": "Huobi",
			"website": "https://www.huobi.com",
			"token": 1001255164573,
			"commission": 0.1,
			"votingPower": 0.010929,
			"rank": 23,
			"jailed": false,
			"participation": 0.0,
			"windowMissCount": 77.5,
			"commissionScore": 50.0,
			"totalScore": 42.5,
			"level": 2
		},
		{
			"address": "bandvaloper1hln9scsl9yqup8nxyum06rmggql5m5zqwxmt3p",
			"moniker": "InfStones",
			"website": "https://infstones.com",
			"token": 1000004132509,
			"commission": 0.1,
			"votingPower": 0.010916,
			"rank": 24,
			"jailed": false,
			"participation": 9.090909090909093,
			"windowMissCount": 85.0,
			"commissionScore": 50.0,
			"totalScore": 48.03030303030303,
			"level": 2
		},
		{
			"address": "bandvaloper1nmlds05h9zpj0m3actleslnmf5ett8xfvmjgju",
			"moniker": "Smart Stake \ud83d\udcc8\ud83d\udcca",
			"website": "analytics.smartstake.io/band",
			"token": 634762013595,
			"commission": 0.05,
			"votingPower": 0.006929,
			"rank": 25,
			"jailed": false,
			"participation": 36.36363636363637,
			"windowMissCount": 100.0,
			"commissionScore": 25.0,
			"totalScore": 53.78787878787879,
			"level": 3
		},
		{
			"address": "bandvaloper1hdw8pzr79y4at0teak0mwcrjhv3e6n3wegfv2m",
			"moniker": "w3coins",
			"website": "https://www.w3coins.io",
			"token": 594584378498,
			"commission": 0.05,
			"votingPower": 0.00649,
			"rank": 26,
			"jailed": false,
			"participation": 18.181818181818176,
			"windowMissCount": 97.8,
			"commissionScore": 25.0,
			"totalScore": 46.99393939393939,
			"level": 2
		},
		{
			"address": "bandvaloper1uytng9pl50mtedmsdrzanvy8vgxttvysw59ugd",
			"moniker": "\ud83e\ude82HighStakes.ch\ud83c\udde8\ud83c\udded",
			"website": "https://highstakes.ch/",
			"token": 541493653536,
			"commission": 0.05,
			"votingPower": 0.005911,
			"rank": 27,
			"jailed": false,
			"participation": 63.63636363636363,
			"windowMissCount": 92.3,
			"commissionScore": 25.0,
			"totalScore": 60.31212121212121,
			"level": 3
		},
		{
			"address": "bandvaloper1unfg2zhnssl07tql8d85zc6rx7zsfs5qh206av",
			"moniker": "StakeCraft",
			"website": "https://stakecraft.com",
			"token": 508128402611,
			"commission": 0.1,
			"votingPower": 0.005547,
			"rank": 28,
			"jailed": false,
			"participation": 27.27272727272727,
			"windowMissCount": 99.3,
			"commissionScore": 50.0,
			"totalScore": 58.85757575757575,
			"level": 3
		},
		{
			"address": "bandvaloper1qzl2ckmfv83w4f65rf77utuc5jmhtexpjxjyzw",
			"moniker": "BitNordic",
			"website": "https://bitnordic.com",
			"token": 501349790290,
			"commission": 0.05,
			"votingPower": 0.005473,
			"rank": 29,
			"jailed": false,
			"participation": 0.0,
			"windowMissCount": 99.6,
			"commissionScore": 25.0,
			"totalScore": 41.53333333333333,
			"level": 2
		},
		{
			"address": "bandvaloper1lvnlajgsn6mkx0p33g7ge6jyfpjlhrpv7clhqk",
			"moniker": "Imperator.co",
			"website": "https://imperator.co",
			"token": 500296545829,
			"commission": 0.05,
			"votingPower": 0.005461,
			"rank": 30,
			"jailed": false,
			"participation": 0.0,
			"windowMissCount": 95.4,
			"commissionScore": 25.0,
			"totalScore": 40.13333333333333,
			"level": 2
		},
		{
			"address": "bandvaloper13vd9rzgytsvcm278ufehsvdvg2kky2djwjguq7",
			"moniker": "0base.vc",
			"website": "https://0base.vc",
			"token": 441829521072,
			"commission": 0.1,
			"votingPower": 0.004823,
			"rank": 31,
			"jailed": false,
			"participation": 72.72727272727273,
			"windowMissCount": 71.0,
			"commissionScore": 50.0,
			"totalScore": 64.57575757575758,
			"level": 3
		},
		{
			"address": "bandvaloper1xs2penspev206jj0egh5qu7qmr6mjzfgj299xl",
			"moniker": " AutoStake \ud83d\udee1\ufe0f Slash Protected",
			"website": "https://autostake.com",
			"token": 430986586947,
			"commission": 0,
			"votingPower": 0.004704,
			"rank": 32,
			"jailed": false,
			"participation": 63.63636363636363,
			"windowMissCount": 93.3,
			"commissionScore": 0,
			"totalScore": 52.31212121212121,
			"level": 3
		},
		{
			"address": "bandvaloper1ev4ylm9q6kyzsck3t6sw0h86zev95cfxzkn4cz",
			"moniker": "\u2705 CryptoCrew Validators #IBCgang",
			"website": "https://ccvalidators.com",
			"token": 336384441678,
			"commission": 0.05,
			"votingPower": 0.003672,
			"rank": 33,
			"jailed": false,
			"participation": 9.090909090909093,
			"windowMissCount": 99.8,
			"commissionScore": 25.0,
			"totalScore": 44.630303030303025,
			"level": 2
		},
		{
			"address": "bandvaloper10s7t8prp0nz36g4dug5ftkm8elyg9hdtlpn6uv",
			"moniker": "StakeLab",
			"website": "https://www.stakelab.fr",
			"token": 325007805171,
			"commission": 0.05,
			"votingPower": 0.003548,
			"rank": 34,
			"jailed": false,
			"participation": 54.54545454545454,
			"windowMissCount": 91.1,
			"commissionScore": 25.0,
			"totalScore": 56.881818181818176,
			"level": 3
		},
		{
			"address": "bandvaloper1cmx8hvx8pn9ezuc57rgy3dqqlkju6uph3mjwxs",
			"moniker": "polkachu.com",
			"website": "https://polkachu.com",
			"token": 304781133840,
			"commission": 0.01,
			"votingPower": 0.003327,
			"rank": 35,
			"jailed": false,
			"participation": 0.0,
			"windowMissCount": 99.7,
			"commissionScore": 5.0,
			"totalScore": 34.9,
			"level": 2
		},
		{
			"address": "bandvaloper1fzhy0swda9ajmtqeh0ch8v59ngnwsy8ys2dhv9",
			"moniker": "Cosmos Spaces",
			"website": "https://cosmos-spaces.zone/",
			"token": 300187505800,
			"commission": 0.05,
			"votingPower": 0.003277,
			"rank": 36,
			"jailed": false,
			"participation": 0.0,
			"windowMissCount": 99.7,
			"commissionScore": 25.0,
			"totalScore": 41.56666666666667,
			"level": 2
		},
		{
			"address": "bandvaloper1ppycvs7hfnw37aghc9mc58zy9al793sr4mwxjg",
			"moniker": "Nodes.Guru",
			"website": "https://stake.nodes.guru",
			"token": 300003500000,
			"commission": 0.1,
			"votingPower": 0.003275,
			"rank": 37,
			"jailed": false,
			"participation": 0.0,
			"windowMissCount": 88.0,
			"commissionScore": 50.0,
			"totalScore": 46.0,
			"level": 2
		},
		{
			"address": "bandvaloper10grrhfawl98ypn5x25zmqcp8f20eg9sw56v3e0",
			"moniker": "Citadel.one",
			"website": "https://citadel.one",
			"token": 272048803865,
			"commission": 0.05,
			"votingPower": 0.00297,
			"rank": 38,
			"jailed": false,
			"participation": 63.63636363636363,
			"windowMissCount": 96.4,
			"commissionScore": 25.0,
			"totalScore": 61.67878787878788,
			"level": 3
		},
		{
			"address": "bandvaloper147k9e3ssy8yh2xjqmgjc8pnvwgzrl4g2fj306s",
			"moniker": "\ud83c\udfb2 Hub",
			"website": "",
			"token": 239380867003,
			"commission": 0.1,
			"votingPower": 0.002613,
			"rank": 39,
			"jailed": false,
			"participation": 54.54545454545454,
			"windowMissCount": 69.7,
			"commissionScore": 50.0,
			"totalScore": 58.081818181818186,
			"level": 3
		},
		{
			"address": "bandvaloper108jvszyayzzaacpscwczj7lvegq799wa9muyyu",
			"moniker": "BitMaxStaking",
			"website": "https://bitmax.io/",
			"token": 99934008388,
			"commission": 0.1,
			"votingPower": 0.001091,
			"rank": 101,
			"jailed": true,
			"windowMissCount": 50,
			"commissionScore": 50.0,
			"totalScore": 33.333333333333336,
			"level": 2
		},
		{
			"address": "bandvaloper1lxqh84ca9x40krrchq9nrdm2hwhyja2q0hc3cl",
			"moniker": "SolidOne",
			"website": "http://SolidOne.io",
			"token": 76993106850,
			"commission": 0.03,
			"votingPower": 0.00084,
			"rank": 40,
			"jailed": false,
			"participation": 54.54545454545454,
			"windowMissCount": 72.6,
			"commissionScore": 15.0,
			"totalScore": 47.381818181818176,
			"level": 2
		},
		{
			"address": "bandvaloper18fdf6hxw2y2u55xwhhplq438awuk52r27a9ghu",
			"moniker": "BandJediTeam",
			"website": "https://twitter.com/BandJediTeam",
			"token": 76501463954,
			"commission": 0.085,
			"votingPower": 0.000835,
			"rank": 41,
			"jailed": false,
			"participation": 0.0,
			"windowMissCount": 96.7,
			"commissionScore": 42.5,
			"totalScore": 46.4,
			"level": 2
		},
		{
			"address": "bandvaloper1595hec3hxlag3a2p97t2geruhv58zmyzr4euux",
			"moniker": "\ud83d\udc20stake.fish",
			"website": "https://stake.fish",
			"token": 76118436992,
			"commission": 0.1,
			"votingPower": 0.000831,
			"rank": 101,
			"jailed": true,
			"windowMissCount": 50,
			"commissionScore": 50.0,
			"totalScore": 33.333333333333336,
			"level": 2
		},
		{
			"address": "bandvaloper1jyze35artdzs5nhvalt6jnatzhg5z88rfpmv27",
			"moniker": "DO NOT DELEGATE | Everstake",
			"website": "https://everstake.one",
			"token": 74924846107,
			"commission": 0.1,
			"votingPower": 0.000818,
			"rank": 101,
			"jailed": true,
			"windowMissCount": 50,
			"commissionScore": 50.0,
			"totalScore": 33.333333333333336,
			"level": 2
		},
		{
			"address": "bandvaloper1plau7keptn9qdt7nmhphltakv5t054f8lgwjdn",
			"moniker": "Meria",
			"website": "www.meria.com",
			"token": 61947052813,
			"commission": 0.05,
			"votingPower": 0.000676,
			"rank": 42,
			"jailed": false,
			"participation": 18.181818181818176,
			"windowMissCount": 76.3,
			"commissionScore": 25.0,
			"totalScore": 39.82727272727272,
			"level": 2
		},
		{
			"address": "bandvaloper1yz8rv4ptfgs5fd68jam3732p9smma7ceun3xqv",
			"moniker": "ICON Foundation",
			"website": "",
			"token": 60890138769,
			"commission": 0.1,
			"votingPower": 0.000665,
			"rank": 43,
			"jailed": false,
			"participation": 9.090909090909093,
			"windowMissCount": 67.8,
			"commissionScore": 50.0,
			"totalScore": 42.2969696969697,
			"level": 2
		},
		{
			"address": "bandvaloper1hcu2spr3r80v36us40mg938f5qhaqq2qeajtfv",
			"moniker": "Stakewolle.com | Auto-compound",
			"website": "https://stakewolle.com",
			"token": 60235010657,
			"commission": 0.05,
			"votingPower": 0.000658,
			"rank": 44,
			"jailed": false,
			"participation": 54.54545454545454,
			"windowMissCount": 27.4,
			"commissionScore": 25.0,
			"totalScore": 35.64848484848485,
			"level": 2
		},
		{
			"address": "bandvaloper1lgctql28g09l4a829teqev0mpqcup6vu2he8el",
			"moniker": "feel-mining",
			"website": "https://feel-mining.com/boutique/staking",
			"token": 53945474905,
			"commission": 0.03,
			"votingPower": 0.000589,
			"rank": 45,
			"jailed": false,
			"windowMissCount": 0,
			"commissionScore": 15.0,
			"totalScore": 5.0,
			"level": 1
		},
		{
			"address": "bandvaloper1g07e0vqcqpxax93uwn8sqgx4tse5n5g5h7vlyg",
			"moniker": "Fantom Foundation",
			"website": "",
			"token": 50035030112,
			"commission": 0.1,
			"votingPower": 0.000546,
			"rank": 46,
			"jailed": false,
			"participation": 18.181818181818176,
			"windowMissCount": 0,
			"commissionScore": 50.0,
			"totalScore": 22.727272727272723,
			"level": 1
		},
		{
			"address": "bandvaloper1vnsqgwu7jxd49u99etdzt028kkgwvuvz5x6lty",
			"moniker": "StakeSabai",
			"website": "https://sabai.finance",
			"token": 43248329137,
			"commission": 0.1,
			"votingPower": 0.000472,
			"rank": 47,
			"jailed": false,
			"participation": 18.181818181818176,
			"windowMissCount": 97.9,
			"commissionScore": 50.0,
			"totalScore": 55.36060606060605,
			"level": 3
		},
		{
			"address": "bandvaloper1r9hjwvxvmdr6vsdwsktjfpnxv6k85jrsyl994n",
			"moniker": "tansawit",
			"website": "",
			"token": 27692956870,
			"commission": 0.1,
			"votingPower": 0.000302,
			"rank": 101,
			"jailed": true,
			"windowMissCount": 50,
			"commissionScore": 50.0,
			"totalScore": 33.333333333333336,
			"level": 2
		},
		{
			"address": "bandvaloper1tfej533yf07npx6cpl989k5mqrpdn4hdsuyqya",
			"moniker": "Antrix Validators",
			"website": "",
			"token": 27562865305,
			"commission": 0.1,
			"votingPower": 0.000301,
			"rank": 48,
			"jailed": false,
			"participation": 18.181818181818176,
			"windowMissCount": 68.0,
			"commissionScore": 50.0,
			"totalScore": 45.3939393939394,
			"level": 2
		},
		{
			"address": "bandvaloper1zsd6xc82dv2lqtt6hx9ew6hptlvtk0nyk7elqw",
			"moniker": "SargatxetPool",
			"website": "",
			"token": 22047272022,
			"commission": 0.1,
			"votingPower": 0.000241,
			"rank": 49,
			"jailed": false,
			"participation": 0.0,
			"windowMissCount": 83.4,
			"commissionScore": 50.0,
			"totalScore": 44.46666666666667,
			"level": 2
		},
		{
			"address": "bandvaloper1q6qvwyffhwv8svkjpghdykupxrfddyje9tq7ky",
			"moniker": "NodeWorks",
			"website": "",
			"token": 21284997913,
			"commission": 0.1,
			"votingPower": 0.000232,
			"rank": 50,
			"jailed": false,
			"participation": 0.0,
			"windowMissCount": 82.7,
			"commissionScore": 50.0,
			"totalScore": 44.23333333333333,
			"level": 2
		},
		{
			"address": "bandvaloper1mfvez2maqvh4p07gvmq67ek2ul3ua4f8lgpg7n",
			"moniker": "\ud83d\ude80 N1 | NodeOne",
			"website": "https://t.me/n1nodeone",
			"token": 16116306181,
			"commission": 0,
			"votingPower": 0.000176,
			"rank": 51,
			"jailed": false,
			"participation": 27.27272727272727,
			"windowMissCount": 97.2,
			"commissionScore": 0,
			"totalScore": 41.49090909090909,
			"level": 2
		},
		{
			"address": "bandvaloper1t87zha6dydy30uz9m7wq0hz6vj6vlrkl7klczh",
			"moniker": "Please redelegate",
			"website": "https://t.me/bandprotocol_japan",
			"token": 15001392715,
			"commission": 0.1,
			"votingPower": 0.000164,
			"rank": 101,
			"jailed": true,
			"windowMissCount": 50,
			"commissionScore": 50.0,
			"totalScore": 33.333333333333336,
			"level": 2
		},
		{
			"address": "bandvaloper1nzfwx85yjjar55fft72vj72lg6pfgzfz6dsrgm",
			"moniker": "Discontinued",
			"website": "",
			"token": 14191657909,
			"commission": 0.05,
			"votingPower": 0.000155,
			"rank": 101,
			"jailed": true,
			"windowMissCount": 50,
			"commissionScore": 25.0,
			"totalScore": 25.0,
			"level": 1
		},
		{
			"address": "bandvaloper1dndwcqre8wjnk4086vr76nu28q5lhnlsu36td8",
			"moniker": "Crypto Lion \ud83e\udd81 (0% fee)",
			"website": "https://cryptolion.finance",
			"token": 7536646558,
			"commission": 0,
			"votingPower": 8.2e-5,
			"rank": 52,
			"jailed": false,
			"participation": 54.54545454545454,
			"windowMissCount": 79.9,
			"commissionScore": 0,
			"totalScore": 44.81515151515151,
			"level": 2
		},
		{
			"address": "bandvaloper13przl6h5hjmms2xcn38uu0zz3p9kzrdm9s7nv6",
			"moniker": "DO NOT DELEGATE | ChainodeTech",
			"website": "https://chainode.tech/",
			"token": 7250715261,
			"commission": 0.07,
			"votingPower": 7.9e-5,
			"rank": 101,
			"jailed": true,
			"windowMissCount": 50,
			"commissionScore": 35.0,
			"totalScore": 28.333333333333332,
			"level": 1
		},
		{
			"address": "bandvaloper1em0rejsr2wva5flz7fv9qkx6wc755cvcqe9teq",
			"moniker": "d3akash.cloud",
			"website": "www.d3akash.cloud",
			"token": 3882559996,
			"commission": 0.02,
			"votingPower": 4.2e-5,
			"rank": 53,
			"jailed": false,
			"participation": 27.27272727272727,
			"windowMissCount": 66.5,
			"commissionScore": 10.0,
			"totalScore": 34.590909090909086,
			"level": 2
		},
		{
			"address": "bandvaloper17zl6zwq26snsvcm5w7yae8ju9glruwmjeg2agj",
			"moniker": "Earn Network",
			"website": "https://earn.network",
			"token": 3863899444,
			"commission": 0.01,
			"votingPower": 4.2e-5,
			"rank": 54,
			"jailed": false,
			"participation": 0.0,
			"windowMissCount": 89.0,
			"commissionScore": 5.0,
			"totalScore": 31.333333333333332,
			"level": 2
		},
		{
			"address": "bandvaloper1hddt2r0e7nfcdmy87xr3nxlzwqxh6fvcvnpceu",
			"moniker": "\u2705ACI69\u269b\ufe0f\ud83c\uddee\ud83c\uddf9| 0% Fees | Airdrop",
			"website": "https://aci69.trading/staking",
			"token": 2958678552,
			"commission": 0.001,
			"votingPower": 3.2e-5,
			"rank": 55,
			"jailed": false,
			"participation": 0.0,
			"windowMissCount": 80.0,
			"commissionScore": 0.5,
			"totalScore": 26.833333333333332,
			"level": 1
		},
		{
			"address": "bandvaloper1ufg3yw83azadqr7g4p88pc3z2uraacwteejqzw",
			"moniker": "ThomasBlock.io",
			"website": "https://www.ThomasBlock.io",
			"token": 2770020360,
			"commission": 0.07,
			"votingPower": 3e-5,
			"rank": 56,
			"jailed": false,
			"participation": 0.0,
			"windowMissCount": 62.5,
			"commissionScore": 35.0,
			"totalScore": 32.5,
			"level": 2
		},
		{
			"address": "bandvaloper1jxv0u20scum4trha72c7ltfgfqef6nsc8nswfv",
			"moniker": "NO-DELIGATE",
			"website": "",
			"token": 2674000000,
			"commission": 0.08,
			"votingPower": 2.9e-5,
			"rank": 101,
			"jailed": true,
			"windowMissCount": 50,
			"commissionScore": 40.0,
			"totalScore": 30.0,
			"level": 2
		},
		{
			"address": "bandvaloper1k7r8pg244papul57vvzd8de8yu3lsng0zrd33u",
			"moniker": "Vixello",
			"website": "https://vixello.com",
			"token": 2177346212,
			"commission": 0.05,
			"votingPower": 2.4e-5,
			"rank": 57,
			"jailed": false,
			"participation": 9.090909090909093,
			"windowMissCount": 69.5,
			"commissionScore": 25.0,
			"totalScore": 34.53030303030303,
			"level": 2
		},
		{
			"address": "bandvaloper1vyv7l5qyakgnz2y006jq2xawdr3hnezxlylgtw",
			"moniker": "MANTRA DAO",
			"website": "https://mantradao.com",
			"token": 2169326148,
			"commission": 0.05,
			"votingPower": 2.4e-5,
			"rank": 58,
			"jailed": false,
			"participation": 9.090909090909093,
			"windowMissCount": 94.2,
			"commissionScore": 25.0,
			"totalScore": 42.76363636363637,
			"level": 2
		},
		{
			"address": "bandvaloper12v3458kg298ckge36lsqafmmggj3pywj062p2q",
			"moniker": "Inter Blockchain Services",
			"website": "https://ibs.team",
			"token": 2075315021,
			"commission": 0.05,
			"votingPower": 2.3e-5,
			"rank": 59,
			"jailed": false,
			"participation": 45.45454545454546,
			"windowMissCount": 99.4,
			"commissionScore": 25.0,
			"totalScore": 56.618181818181824,
			"level": 3
		},
		{
			"address": "bandvaloper17s35yz3rglx7pnjppm4u9l9ht2k9mr9tq0eyh6",
			"moniker": "Stakeflow",
			"website": "https://validator.stakeflow.io",
			"token": 1802439562,
			"commission": 0.07,
			"votingPower": 2e-5,
			"rank": 60,
			"jailed": false,
			"participation": 36.36363636363637,
			"windowMissCount": 99.2,
			"commissionScore": 35.0,
			"totalScore": 56.85454545454545,
			"level": 3
		},
		{
			"address": "bandvaloper1xhhxypktn0v6zund3nzkfv5gfvs0ughe234xl9",
			"moniker": "blockscape",
			"website": "https://blockscape.network/",
			"token": 1697752949,
			"commission": 0.05,
			"votingPower": 1.9e-5,
			"rank": 61,
			"jailed": false,
			"participation": 54.54545454545454,
			"windowMissCount": 73.4,
			"commissionScore": 25.0,
			"totalScore": 50.98181818181818,
			"level": 3
		},
		{
			"address": "bandvaloper12vctshhhpksuxfmkslrqqg74euesvskxchvnqd",
			"moniker": "Bi23 Labs",
			"website": "https://bi23.com",
			"token": 1683614191,
			"commission": 0.01,
			"votingPower": 1.8e-5,
			"rank": 101,
			"jailed": true,
			"windowMissCount": 50,
			"commissionScore": 5.0,
			"totalScore": 18.333333333333332,
			"level": 1
		},
		{
			"address": "bandvaloper14m538kv607xpcvpef6zrk2uhavpr8katfq2s8z",
			"moniker": "Woodstock",
			"website": "https://woodstockfund.com/",
			"token": 1623334169,
			"commission": 0.08,
			"votingPower": 1.8e-5,
			"rank": 101,
			"jailed": true,
			"windowMissCount": 50,
			"commissionScore": 40.0,
			"totalScore": 30.0,
			"level": 2
		},
		{
			"address": "bandvaloper13jgj2fu2wc0pff7wnsang3m9xt3k67u8zdd5n5",
			"moniker": "TaiPanich",
			"website": "",
			"token": 1359602546,
			"commission": 0.05,
			"votingPower": 1.5e-5,
			"rank": 62,
			"jailed": false,
			"participation": 0.0,
			"windowMissCount": 65.5,
			"commissionScore": 25.0,
			"totalScore": 30.166666666666668,
			"level": 2
		},
		{
			"address": "bandvaloper1c6u3225mjp7a9pa7wh9qky9gd5zjygwq7ntwyj",
			"moniker": "PoorButHappy",
			"website": "https://poorbuthappy.xyz",
			"token": 1251354471,
			"commission": 0,
			"votingPower": 1.4e-5,
			"rank": 63,
			"jailed": false,
			"participation": 0.0,
			"windowMissCount": 96.6,
			"commissionScore": 0,
			"totalScore": 32.199999999999996,
			"level": 2
		},
		{
			"address": "bandvaloper17fjwhmuvgh8lugky0kgz0ejzrt5zplp83zq0l7",
			"moniker": "StakeProof.xyz",
			"website": "https://stakeproof.xyz",
			"token": 1204760287,
			"commission": 0.01,
			"votingPower": 1.3e-5,
			"rank": 101,
			"jailed": true,
			"windowMissCount": 50,
			"commissionScore": 5.0,
			"totalScore": 18.333333333333332,
			"level": 1
		},
		{
			"address": "bandvaloper1qf73zvv3jquf2znwx2qc7tkmgtz7tvq4dn65u7",
			"moniker": "Anchor Staking",
			"website": "https://www.anchorstaking.com",
			"token": 1137009774,
			"commission": 0.03,
			"votingPower": 1.2e-5,
			"rank": 64,
			"jailed": false,
			"participation": 0.0,
			"windowMissCount": 95.1,
			"commissionScore": 15.0,
			"totalScore": 36.699999999999996,
			"level": 2
		},
		{
			"address": "bandvaloper17dw8k6t26r4ueylctf792qssy6sscu93sucxvh",
			"moniker": "Bitcoin Addict Thailand",
			"website": "https://bitcoinaddict.org",
			"token": 1079008944,
			"commission": 0.1,
			"votingPower": 1.2e-5,
			"rank": 101,
			"jailed": true,
			"windowMissCount": 50,
			"commissionScore": 50.0,
			"totalScore": 33.333333333333336,
			"level": 2
		},
		{
			"address": "bandvaloper1kkaderm3sae8l33pmv47rr5u6k4pzy0rgs9ryx",
			"moniker": "PerfectStake",
			"website": "",
			"token": 939125485,
			"commission": 0.02,
			"votingPower": 1e-5,
			"rank": 101,
			"jailed": true,
			"windowMissCount": 50,
			"commissionScore": 10.0,
			"totalScore": 20.0,
			"level": 1
		},
		{
			"address": "bandvaloper168ttwa8uvewknhuces66hsx8l08tyn9027usv6",
			"moniker": "openstake.net",
			"website": "https://openstake.net",
			"token": 830820000,
			"commission": 0,
			"votingPower": 9e-6,
			"rank": 65,
			"jailed": false,
			"participation": 27.27272727272727,
			"windowMissCount": 50,
			"commissionScore": 0,
			"totalScore": 25.757575757575754,
			"level": 1
		},
		{
			"address": "bandvaloper1p26kdh5fx24qz9xa5jtjje8ha8ee9q44nrsc8c",
			"moniker": "Stakecito",
			"website": "https://www.stakecito.com",
			"token": 750820033,
			"commission": 0.05,
			"votingPower": 8e-6,
			"rank": 66,
			"jailed": false,
			"participation": 0.0,
			"windowMissCount": 96.5,
			"commissionScore": 25.0,
			"totalScore": 40.5,
			"level": 2
		},
		{
			"address": "bandvaloper157vs5a5tqt2kkkht95azwg9pa77z8hwk3ae5ee",
			"moniker": "DECALI.io",
			"website": "https://decali.io",
			"token": 735991776,
			"commission": 0.05,
			"votingPower": 8e-6,
			"rank": 67,
			"jailed": false,
			"participation": 27.27272727272727,
			"windowMissCount": 99.9,
			"commissionScore": 25.0,
			"totalScore": 50.724242424242426,
			"level": 3
		},
		{
			"address": "bandvaloper1l8zzhhe3ltlkk7sd38rcw7u6g9d609t2etc2zp",
			"moniker": "node101",
			"website": "",
			"token": 732480530,
			"commission": 0.05,
			"votingPower": 8e-6,
			"rank": 68,
			"jailed": false,
			"participation": 18.181818181818176,
			"windowMissCount": 0,
			"commissionScore": 25.0,
			"totalScore": 14.393939393939391,
			"level": 1
		},
		{
			"address": "bandvaloper16c9s32mr3q59w6dupwreh5yyzu20nlp3ctxapu",
			"moniker": "Atlas Staking (-- Auto compound rewards --)",
			"website": "www.atlas-staking.com/staking-band/",
			"token": 691388430,
			"commission": 0.05,
			"votingPower": 8e-6,
			"rank": 69,
			"jailed": false,
			"participation": 27.27272727272727,
			"windowMissCount": 87.0,
			"commissionScore": 25.0,
			"totalScore": 46.424242424242415,
			"level": 2
		},
		{
			"address": "bandvaloper1wwl9d8gvpktdjhdpzxe9yupunpkthzayysf2hn",
			"moniker": "Architect Nodes",
			"website": "https://www.architectnodes.com",
			"token": 327705176,
			"commission": 0.05,
			"votingPower": 4e-6,
			"rank": 70,
			"jailed": false,
			"participation": 36.36363636363637,
			"windowMissCount": 97.9,
			"commissionScore": 25.0,
			"totalScore": 53.08787878787879,
			"level": 3
		},
		{
			"address": "bandvaloper1y0pw9v0km2a9dx0gvlc5hvuk4vjwgsv94mds98",
			"moniker": "Woodstock Fund",
			"website": "www.woodstockfund.com",
			"token": 279550545,
			"commission": 0.1,
			"votingPower": 3e-6,
			"rank": 101,
			"jailed": true,
			"windowMissCount": 50,
			"commissionScore": 50.0,
			"totalScore": 33.333333333333336,
			"level": 2
		},
		{
			"address": "bandvaloper1fyn907tzlxknxgmvkjvmhgksf7t3zwjlcd6a0a",
			"moniker": "DO NOT DELEGATE | Chorus One",
			"website": "https://chorus.one/",
			"token": 247209695,
			"commission": 0.12,
			"votingPower": 3e-6,
			"rank": 101,
			"jailed": true,
			"windowMissCount": 50,
			"commissionScore": 60.0,
			"totalScore": 36.666666666666664,
			"level": 2
		},
		{
			"address": "bandvaloper1yt682mnahn52zqv8pfukr43mqjys9nf22cq3td",
			"moniker": "DO NOT DELEGATE",
			"website": "",
			"token": 240260724,
			"commission": 0.045,
			"votingPower": 3e-6,
			"rank": 101,
			"jailed": true,
			"windowMissCount": 50,
			"commissionScore": 22.499999999999996,
			"totalScore": 24.166666666666668,
			"level": 1
		},
		{
			"address": "bandvaloper1z5nwqcxltx89zt07jmw9jtx2jlerawsauptl6j",
			"moniker": "Trivium | Trivium.Network",
			"website": "https://trivium.network",
			"token": 212000000,
			"commission": 0.01,
			"votingPower": 2e-6,
			"rank": 71,
			"jailed": false,
			"participation": 18.181818181818176,
			"windowMissCount": 99.8,
			"commissionScore": 5.0,
			"totalScore": 40.99393939393939,
			"level": 2
		},
		{
			"address": "bandvaloper1k8u9cqf6ejr5nm7prxk46el4gcxvv58clx8j9m",
			"moniker": "Staky.io",
			"website": "",
			"token": 208383924,
			"commission": 0.03,
			"votingPower": 2e-6,
			"rank": 101,
			"jailed": true,
			"windowMissCount": 50,
			"commissionScore": 15.0,
			"totalScore": 21.666666666666668,
			"level": 1
		},
		{
			"address": "bandvaloper1ejnk6k8ny3y5kwr234m3y32p7dxsx2a0wvcpyl",
			"moniker": "\ud83c\udf52 Ryabina.io \ud83c\udf52",
			"website": "https://ryabina.io",
			"token": 201313757,
			"commission": 0.0999,
			"votingPower": 2e-6,
			"rank": 101,
			"jailed": true,
			"windowMissCount": 50,
			"commissionScore": 49.95,
			"totalScore": 33.31666666666667,
			"level": 2
		},
		{
			"address": "bandvaloper1nmd2mmxve9t0qca5ln8zqak7dlhrxylf0xw5zs",
			"moniker": "Chainnodes",
			"website": "https://chainnodes.net",
			"token": 167941398,
			"commission": 0.02,
			"votingPower": 2e-6,
			"rank": 72,
			"jailed": false,
			"participation": 45.45454545454546,
			"windowMissCount": 95.3,
			"commissionScore": 10.0,
			"totalScore": 50.25151515151515,
			"level": 3
		},
		{
			"address": "bandvaloper16rfxcd3geg4m8rlc29jk4mlvjn77lem8m2fl6h",
			"moniker": "HOKUTO",
			"website": "",
			"token": 158815079,
			"commission": 0.1,
			"votingPower": 2e-6,
			"rank": 101,
			"jailed": true,
			"windowMissCount": 50,
			"commissionScore": 50.0,
			"totalScore": 33.333333333333336,
			"level": 2
		},
		{
			"address": "bandvaloper19huytqr8srz9wcdhvas5cvxddg8dtqcv6tce0s",
			"moniker": "Notional",
			"website": "https://github.com/notional-labs",
			"token": 147841309,
			"commission": 0.0969,
			"votingPower": 2e-6,
			"rank": 101,
			"jailed": true,
			"windowMissCount": 50,
			"commissionScore": 48.449999999999996,
			"totalScore": 32.81666666666666,
			"level": 2
		},
		{
			"address": "bandvaloper1n7jc3hyxsdj693qpwvnzcer5cluuadj7lq5u38",
			"moniker": "F5 Nodes",
			"website": "https://f5nodes.com",
			"token": 115019900,
			"commission": 0.1,
			"votingPower": 1e-6,
			"rank": 73,
			"jailed": false,
			"participation": 0.0,
			"windowMissCount": 99.6,
			"commissionScore": 50.0,
			"totalScore": 49.86666666666667,
			"level": 2
		},
		{
			"address": "bandvaloper1symf474wnypes2d3mecllqk6l26rwz8melsedq",
			"moniker": "BlockHunters \ud83c\udfaf",
			"website": "https://blockhunters.org/",
			"token": 114161629,
			"commission": 0.04777,
			"votingPower": 1e-6,
			"rank": 101,
			"jailed": true,
			"windowMissCount": 50,
			"commissionScore": 23.884999999999998,
			"totalScore": 24.62833333333333,
			"level": 1
		},
		{
			"address": "bandvaloper10cr7hwv22fwazn68azcqgegv8vj6xnlztnt5s0",
			"moniker": "GateOmega",
			"website": "https://gateomega.com",
			"token": 110000000,
			"commission": 0.1,
			"votingPower": 1e-6,
			"rank": 74,
			"jailed": false,
			"participation": 0.0,
			"windowMissCount": 93.2,
			"commissionScore": 50.0,
			"totalScore": 47.73333333333333,
			"level": 2
		},
		{
			"address": "bandvaloper1q4nrju47un2hchqvxkynyfknav0anf6uhya2h6",
			"moniker": "AG",
			"website": "https://agx10k.ml",
			"token": 107487437,
			"commission": 0.05,
			"votingPower": 1e-6,
			"rank": 101,
			"jailed": true,
			"windowMissCount": 50,
			"commissionScore": 25.0,
			"totalScore": 25.0,
			"level": 1
		},
		{
			"address": "bandvaloper1um2flgfvteyyjsaxf85tjku8tdhcqhtpwaxpat",
			"moniker": "SeaX Ventures",
			"website": "https://www.linkedin.com/company/seax-ventures/",
			"token": 105999463,
			"commission": 0.06,
			"votingPower": 1e-6,
			"rank": 101,
			"jailed": true,
			"windowMissCount": 50,
			"commissionScore": 30.0,
			"totalScore": 26.666666666666668,
			"level": 1
		},
		{
			"address": "bandvaloper18plz4ccc6x6heetcfxsx7vc9n3cmtj56huztxe",
			"moniker": "DLINODES.COM",
			"website": "\u201chttps://dlinodes.com\u201d",
			"token": 100179764,
			"commission": 0.0777,
			"votingPower": 1e-6,
			"rank": 101,
			"jailed": true,
			"windowMissCount": 50,
			"commissionScore": 38.85,
			"totalScore": 29.616666666666664,
			"level": 1
		},
		{
			"address": "bandvaloper1l6sskrveh0afjeqm7mn9lm83xlulkwg7z8sdqy",
			"moniker": "StakeTown",
			"website": "",
			"token": 100000000,
			"commission": 0.05,
			"votingPower": 1e-6,
			"rank": 75,
			"jailed": false,
			"participation": 0.0,
			"windowMissCount": 91.6,
			"commissionScore": 25.0,
			"totalScore": 38.86666666666667,
			"level": 2
		},
		{
			"address": "bandvaloper1q4sta02v9tfssnsdnpj3ephygay2vdelqdqaup",
			"moniker": "Jelly",
			"website": "",
			"token": 83983700,
			"commission": 0.05,
			"votingPower": 1e-6,
			"rank": 76,
			"jailed": false,
			"participation": 9.090909090909093,
			"windowMissCount": 90.3,
			"commissionScore": 25.0,
			"totalScore": 41.46363636363636,
			"level": 2
		},
		{
			"address": "bandvaloper1h9a8wasp8zvj8h06mp7tlm0eetgacafkyfqapc",
			"moniker": "TienThuatToan",
			"website": "https://tienthuattoan.ventures",
			"token": 80702830,
			"commission": 0.01,
			"votingPower": 1e-6,
			"rank": 77,
			"jailed": false,
			"participation": 0.0,
			"windowMissCount": 92.5,
			"commissionScore": 5.0,
			"totalScore": 32.5,
			"level": 2
		},
		{
			"address": "bandvaloper1apk4t9v58tc3pwnf2e532x9dmk2ev2n3l86402",
			"moniker": "Closed, Please redelegate",
			"website": "https://dhk.org",
			"token": 80200000,
			"commission": 0.05,
			"votingPower": 1e-6,
			"rank": 101,
			"jailed": true,
			"windowMissCount": 50,
			"commissionScore": 25.0,
			"totalScore": 25.0,
			"level": 1
		},
		{
			"address": "bandvaloper1w7k4mfls32c2ungqstgeetguacm07gh9sa6ze8",
			"moniker": " kjnodes.com \ud83e\udd84",
			"website": "https://services.kjnodes.com/mainnet/band",
			"token": 70000000,
			"commission": 0.05,
			"votingPower": 1e-6,
			"rank": 78,
			"jailed": false,
			"participation": 0.0,
			"windowMissCount": 50,
			"commissionScore": 25.0,
			"totalScore": 25.0,
			"level": 1
		},
		{
			"address": "bandvaloper1y42hgl7dgxswpe3mv5gknsrzfn9xy4t44ep6yh",
			"moniker": "Consensus One",
			"website": "https://www.consensus.one",
			"token": 63000000,
			"commission": 0.05,
			"votingPower": 1e-6,
			"rank": 79,
			"jailed": false,
			"participation": 9.090909090909093,
			"windowMissCount": 85.9,
			"commissionScore": 25.0,
			"totalScore": 39.9969696969697,
			"level": 2
		},
		{
			"address": "bandvaloper1ty2mytdkel96e8llkaezn43vnj0ghm4p5dl8xv",
			"moniker": "Valnodes - Carbon Neutral Staking",
			"website": "https://www.valnodes.com",
			"token": 60564354,
			"commission": 0.0314,
			"votingPower": 1e-6,
			"rank": 101,
			"jailed": true,
			"windowMissCount": 50,
			"commissionScore": 15.699999999999998,
			"totalScore": 21.900000000000002,
			"level": 1
		},
		{
			"address": "bandvaloper13fwr8rmugu2mfuurfx4sfmyv05haw9sujnqzd8",
			"moniker": "Please REDELEGATE to StakeCraft in example - closing here at 25th may",
			"website": "offline",
			"token": 54879762,
			"commission": 0.1,
			"votingPower": 1e-6,
			"rank": 101,
			"jailed": true,
			"windowMissCount": 50,
			"commissionScore": 50.0,
			"totalScore": 33.333333333333336,
			"level": 2
		},
		{
			"address": "bandvaloper1k85y0j5dg6l9cqc793vut85wawm460sljv9y28",
			"moniker": "PHnetwork",
			"website": "https://www.phnetwork.org",
			"token": 50219074,
			"commission": 0.1,
			"votingPower": 1e-6,
			"rank": 101,
			"jailed": true,
			"windowMissCount": 50,
			"commissionScore": 50.0,
			"totalScore": 33.333333333333336,
			"level": 2
		},
		{
			"address": "bandvaloper16n2cazl94n47zknt5uspxgv90p23wpek6agqe2",
			"moniker": "Closing - Please redelegate",
			"website": "https://cryptostacking.network",
			"token": 44969136,
			"commission": 0,
			"votingPower": 0,
			"rank": 101,
			"jailed": true,
			"windowMissCount": 50,
			"commissionScore": 0,
			"totalScore": 16.666666666666668,
			"level": 1
		},
		{
			"address": "bandvaloper13d3krtk9lwkl8d07pg92090f9xrgwywd7f58kn",
			"moniker": "[DECOMMISSIONED] AUDIT.one",
			"website": "",
			"token": 42550179,
			"commission": 0.07,
			"votingPower": 0,
			"rank": 101,
			"jailed": true,
			"windowMissCount": 50,
			"commissionScore": 35.0,
			"totalScore": 28.333333333333332,
			"level": 1
		},
		{
			"address": "bandvaloper1pjhgksl4nhrahxam6l6fg4v8z8r5c68504szuq",
			"moniker": "1ce",
			"website": "",
			"token": 39000000,
			"commission": 0.1,
			"votingPower": 0,
			"rank": 80,
			"jailed": false,
			"participation": 0.0,
			"windowMissCount": 92.3,
			"commissionScore": 50.0,
			"totalScore": 47.43333333333334,
			"level": 2
		},
		{
			"address": "bandvaloper1l2zm3g6l0aqrcwn84g4540krglmd4vvywd86w3",
			"moniker": "retz80",
			"website": "https://www.retz80.com",
			"token": 38790000,
			"commission": 0.09,
			"votingPower": 0,
			"rank": 101,
			"jailed": true,
			"windowMissCount": 50,
			"commissionScore": 44.99999999999999,
			"totalScore": 31.666666666666668,
			"level": 2
		},
		{
			"address": "bandvaloper13w67kucjvfcjr3du33fptqqpag5cgjqksv9sxt",
			"moniker": "Cryptonian | Auto-compound",
			"website": "https://band.cryptonian.life",
			"token": 35726210,
			"commission": 0.01,
			"votingPower": 0,
			"rank": 81,
			"jailed": false,
			"participation": 0.0,
			"windowMissCount": 90.3,
			"commissionScore": 5.0,
			"totalScore": 31.766666666666666,
			"level": 2
		},
		{
			"address": "bandvaloper1vjlsw58ap5gdvw6w7z7mjnh38ukdg3xw708wqu",
			"moniker": "DO NOT DELEGATE | 0base.vc",
			"website": "https://www.notion.so/BAND-Double-Signing-3732445-4016c029dcb147e0b278952c38775af9",
			"token": 33826854,
			"commission": 0,
			"votingPower": 0,
			"rank": 101,
			"jailed": true,
			"windowMissCount": 50,
			"commissionScore": 0,
			"totalScore": 16.666666666666668,
			"level": 1
		},
		{
			"address": "bandvaloper13tf84rkc9yflru6kty4xj8jtkuzl6fd66f3q3z",
			"moniker": "RoomIT",
			"website": "https://roomit.xyz",
			"token": 27675543,
			"commission": 0.1,
			"votingPower": 0,
			"rank": 82,
			"jailed": false,
			"participation": 0.0,
			"windowMissCount": 80.4,
			"commissionScore": 50.0,
			"totalScore": 43.46666666666667,
			"level": 2
		},
		{
			"address": "bandvaloper1wlgfyk9mx9ms6jgvupxmx6dl0f85xmvrtdpdew",
			"moniker": "indistock",
			"website": "",
			"token": 24996600,
			"commission": 0.1,
			"votingPower": 0,
			"rank": 101,
			"jailed": true,
			"windowMissCount": 50,
			"commissionScore": 50.0,
			"totalScore": 33.333333333333336,
			"level": 2
		},
		{
			"address": "bandvaloper157jzxupqvcrk29cmdnxgwpy947za08aw9tq5re",
			"moniker": "FullStake.li",
			"website": "https://www.fullstake.li",
			"token": 20997900,
			"commission": 0,
			"votingPower": 0,
			"rank": 101,
			"jailed": true,
			"windowMissCount": 50,
			"commissionScore": 0,
			"totalScore": 16.666666666666668,
			"level": 1
		},
		{
			"address": "bandvaloper1vsdzup4ucv28vcp8lgwe7t4jympkwjwzcga0zp",
			"moniker": "BlockShark",
			"website": "https://www.blockshark.net",
			"token": 19500000,
			"commission": 0.03,
			"votingPower": 0,
			"rank": 83,
			"jailed": false,
			"participation": 0.0,
			"windowMissCount": 69.6,
			"commissionScore": 15.0,
			"totalScore": 28.2,
			"level": 1
		},
		{
			"address": "bandvaloper12ne95rsea79n9d8sflxa5mxd6egdmlyzkryz3e",
			"moniker": "Blackhox",
			"website": "https://github.com/blackhox/AboutMe",
			"token": 19000000,
			"commission": 0.05,
			"votingPower": 0,
			"rank": 84,
			"jailed": false,
			"participation": 0.0,
			"windowMissCount": 98.8,
			"commissionScore": 25.0,
			"totalScore": 41.266666666666666,
			"level": 2
		},
		{
			"address": "bandvaloper1c34u63fdagur6xfmnu2d50242d3kszl9wnulk8",
			"moniker": "ARCTIC",
			"website": "https://arctics.wtf",
			"token": 16009500,
			"commission": 0.05,
			"votingPower": 0,
			"rank": 85,
			"jailed": false,
			"participation": 0.0,
			"windowMissCount": 93.9,
			"commissionScore": 25.0,
			"totalScore": 39.63333333333333,
			"level": 2
		},
		{
			"address": "bandvaloper1xv0tggalann54lrfj47pf6gv7rs9q0m7047gr0",
			"moniker": "ACI69",
			"website": "",
			"token": 14607080,
			"commission": 0.01,
			"votingPower": 0,
			"rank": 101,
			"jailed": true,
			"windowMissCount": 50,
			"commissionScore": 5.0,
			"totalScore": 18.333333333333332,
			"level": 1
		},
		{
			"address": "bandvaloper15nnme8tz4hqvcd9aufjetemwf9py20khaannu2",
			"moniker": "Nosce",
			"website": "",
			"token": 10997999,
			"commission": 0.05,
			"votingPower": 0,
			"rank": 101,
			"jailed": true,
			"windowMissCount": 50,
			"commissionScore": 25.0,
			"totalScore": 25.0,
			"level": 1
		},
		{
			"address": "bandvaloper1359wrxxvs2js7vrant548af4zp72hu2mgftm2e",
			"moniker": "landeros | StakeUp",
			"website": "https://stakeup.tech",
			"token": 10070060,
			"commission": 0.1,
			"votingPower": 0,
			"rank": 86,
			"jailed": false,
			"participation": 0.0,
			"windowMissCount": 90.1,
			"commissionScore": 50.0,
			"totalScore": 46.699999999999996,
			"level": 2
		},
		{
			"address": "bandvaloper1pp534se9rmt59d5zkv4p8cp6jj5zxm4uxdhejs",
			"moniker": "Enigma",
			"website": "https://enigma-validator.com/",
			"token": 10000000,
			"commission": 0.05,
			"votingPower": 0,
			"rank": 87,
			"jailed": false,
			"participation": 0.0,
			"windowMissCount": 89.9,
			"commissionScore": 25.0,
			"totalScore": 38.300000000000004,
			"level": 2
		},
		{
			"address": "bandvaloper15mpftgqh4w8dz5ayaeq49s4n8lmyx27kee74zf",
			"moniker": "Chainp2p",
			"website": "",
			"token": 10000000,
			"commission": 0.03,
			"votingPower": 0,
			"rank": 88,
			"jailed": false,
			"participation": 0.0,
			"windowMissCount": 68.6,
			"commissionScore": 15.0,
			"totalScore": 27.866666666666664,
			"level": 1
		},
		{
			"address": "bandvaloper1d00ke0s7r2eqjg4qf0p2rwtc72cdql9p3zskhn",
			"moniker": "Mintia Decentralized | No slashing",
			"website": "",
			"token": 9999010,
			"commission": 0,
			"votingPower": 0,
			"rank": 101,
			"jailed": true,
			"windowMissCount": 50,
			"commissionScore": 0,
			"totalScore": 16.666666666666668,
			"level": 1
		},
		{
			"address": "bandvaloper17fhw72gsrhnucyzfag068yhsp3kj5yeu0xu5x2",
			"moniker": "Nodeist",
			"website": "https://nodeist.net",
			"token": 9998100,
			"commission": 0.05,
			"votingPower": 0,
			"rank": 101,
			"jailed": true,
			"windowMissCount": 50,
			"commissionScore": 25.0,
			"totalScore": 25.0,
			"level": 1
		},
		{
			"address": "bandvaloper1jf2rqyr2ud20asyzscvrzh65s234eycx86lzcn",
			"moniker": "Node&Validator VN",
			"website": "https://linktr.ee/validatorvn",
			"token": 9506773,
			"commission": 0,
			"votingPower": 0,
			"rank": 89,
			"jailed": false,
			"participation": 0.0,
			"windowMissCount": 0,
			"commissionScore": 0,
			"totalScore": 0.0,
			"level": 1
		},
		{
			"address": "bandvaloper1w4jrw76q55vksjjm9d9qx76auyk8gxkhdtllgv",
			"moniker": "RN0X",
			"website": "",
			"token": 8999286,
			"commission": 0.1,
			"votingPower": 0,
			"rank": 101,
			"jailed": true,
			"windowMissCount": 50,
			"commissionScore": 50.0,
			"totalScore": 33.333333333333336,
			"level": 2
		},
		{
			"address": "bandvaloper1fd9m05k39lrwq2qyw3rszt7wumdm2s5m42k2n2",
			"moniker": "Wetez",
			"website": "",
			"token": 8095791,
			"commission": 0.1,
			"votingPower": 0,
			"rank": 101,
			"jailed": true,
			"windowMissCount": 50,
			"commissionScore": 50.0,
			"totalScore": 33.333333333333336,
			"level": 2
		},
		{
			"address": "bandvaloper1e2ksk2qw5wk4a996kj0mp9gucpr96ljnf3r358",
			"moniker": "\ud83d\udd25STAVR\ud83d\udd25",
			"website": "https://github.com/obajay",
			"token": 8036748,
			"commission": 0.1,
			"votingPower": 0,
			"rank": 90,
			"jailed": false,
			"participation": 0.0,
			"windowMissCount": 92.3,
			"commissionScore": 50.0,
			"totalScore": 47.43333333333334,
			"level": 2
		},
		{
			"address": "bandvaloper17vzyy636a3zluzrq7u7mhrkl3wrfa29wh7lg6p",
			"moniker": "Lefey",
			"website": "https://github.com/Lefey",
			"token": 8000000,
			"commission": 0.1,
			"votingPower": 0,
			"rank": 91,
			"jailed": false,
			"participation": 0.0,
			"windowMissCount": 50,
			"commissionScore": 50.0,
			"totalScore": 33.333333333333336,
			"level": 2
		},
		{
			"address": "bandvaloper1gskdp65zqm8cz9u5tkypycz33jh5g0hyvgdzzq",
			"moniker": "SerGo",
			"website": "https://sergo.dev",
			"token": 7370000,
			"commission": 0.1,
			"votingPower": 0,
			"rank": 92,
			"jailed": false,
			"participation": 0.0,
			"windowMissCount": 96.5,
			"commissionScore": 50.0,
			"totalScore": 48.833333333333336,
			"level": 2
		},
		{
			"address": "bandvaloper1y6cjh2xy6550kw63wxzgyse85vxues809z3sys",
			"moniker": "Frens (\ud83e\udd1d,\ud83e\udd1d)",
			"website": "https://frens.army",
			"token": 7299959,
			"commission": 0.05,
			"votingPower": 0,
			"rank": 93,
			"jailed": false,
			"participation": 0.0,
			"windowMissCount": 98.3,
			"commissionScore": 25.0,
			"totalScore": 41.1,
			"level": 2
		},
		{
			"address": "bandvaloper1f3fxlynz5jdpnf77g9es0cjxwlwr05sc8tz0fe",
			"moniker": "Biker4b",
			"website": "",
			"token": 7179300,
			"commission": 0.05,
			"votingPower": 0,
			"rank": 101,
			"jailed": true,
			"windowMissCount": 50,
			"commissionScore": 25.0,
			"totalScore": 25.0,
			"level": 1
		},
		{
			"address": "bandvaloper18pvhw57fxtt0yh4ut55f2k9adshzyp7mqsu36y",
			"moniker": "skynodes",
			"website": "www.skynodejs.net",
			"token": 7161981,
			"commission": 0.01,
			"votingPower": 0,
			"rank": 94,
			"jailed": false,
			"participation": 0.0,
			"windowMissCount": 50,
			"commissionScore": 5.0,
			"totalScore": 18.333333333333332,
			"level": 1
		},
		{
			"address": "bandvaloper1h8rpvkrpcv8pvycjf7dpqmnpljse93msnqdsfl",
			"moniker": "ruangnode",
			"website": "https://ruangnode.com",
			"token": 7100000,
			"commission": 0.1,
			"votingPower": 0,
			"rank": 95,
			"jailed": false,
			"participation": 0.0,
			"windowMissCount": 50,
			"commissionScore": 50.0,
			"totalScore": 33.333333333333336,
			"level": 2
		},
		{
			"address": "bandvaloper1m0pn05sa397rtjxkjxj2vrms4cj60ugd7yhzlw",
			"moniker": "EthicalNode",
			"website": "",
			"token": 6400000,
			"commission": 0.05,
			"votingPower": 0,
			"rank": 96,
			"jailed": false,
			"participation": 0.0,
			"windowMissCount": 88.7,
			"commissionScore": 25.0,
			"totalScore": 37.9,
			"level": 2
		},
		{
			"address": "bandvaloper1v8ghn09qv5jzxd8g7unsttrqntn67gkth5eq5f",
			"moniker": "Helion Band Validator",
			"website": "",
			"token": 5999400,
			"commission": 0.1,
			"votingPower": 0,
			"rank": 101,
			"jailed": true,
			"windowMissCount": 50,
			"commissionScore": 50.0,
			"totalScore": 33.333333333333336,
			"level": 2
		},
		{
			"address": "bandvaloper1hg2p4397wssj8ttger9rphafxpcdz6nvngskxr",
			"moniker": "BANDITS",
			"website": "https://discord.com/invite/ZkAcYV5",
			"token": 5887360,
			"commission": 0,
			"votingPower": 0,
			"rank": 101,
			"jailed": true,
			"windowMissCount": 50,
			"commissionScore": 0,
			"totalScore": 16.666666666666668,
			"level": 1
		},
		{
			"address": "bandvaloper1q9mm0uxakk4w0tjyccjhtdzyardesv5ynvw03e",
			"moniker": "DiBugNodes",
			"website": "https://www.dibugnodes.com/",
			"token": 5200000,
			"commission": 0.05,
			"votingPower": 0,
			"rank": 97,
			"jailed": false,
			"participation": 0.0,
			"windowMissCount": 99.0,
			"commissionScore": 25.0,
			"totalScore": 41.333333333333336,
			"level": 2
		},
		{
			"address": "bandvaloper1etjk0kcrw808jf80mhhc8mx80w34agw5rnnnsz",
			"moniker": "dnsarz",
			"website": "https://dnsarz.xyz",
			"token": 5132738,
			"commission": 0.1,
			"votingPower": 0,
			"rank": 101,
			"jailed": true,
			"windowMissCount": 50,
			"commissionScore": 50.0,
			"totalScore": 33.333333333333336,
			"level": 2
		},
		{
			"address": "bandvaloper1pvwmcawgl0h8cwje2gcv46r9l34u9crc8tc6hj",
			"moniker": "STAKKY",
			"website": "",
			"token": 5000000,
			"commission": 0.05,
			"votingPower": 0,
			"rank": 98,
			"jailed": false,
			"participation": 0.0,
			"windowMissCount": 50,
			"commissionScore": 25.0,
			"totalScore": 25.0,
			"level": 1
		},
		{
			"address": "bandvaloper1wdlz48hczmy36le8uyehl52sk8hya7hwtfm9pl",
			"moniker": "stanisloe | 2pilot",
			"website": "https://2pilot.dev",
			"token": 5000000,
			"commission": 0.05,
			"votingPower": 0,
			"rank": 99,
			"jailed": false,
			"participation": 0.0,
			"windowMissCount": 50,
			"commissionScore": 25.0,
			"totalScore": 25.0,
			"level": 1
		},
		{
			"address": "bandvaloper19esqej9q2uffhjj5d3d23lsd0fuafxhdm98g2d",
			"moniker": "pathrock-mclb",
			"website": "",
			"token": 4999505,
			"commission": 0.1,
			"votingPower": 0,
			"rank": 101,
			"jailed": true,
			"windowMissCount": 50,
			"commissionScore": 50.0,
			"totalScore": 33.333333333333336,
			"level": 2
		},
		{
			"address": "bandvaloper1e794d7mk245mr62e6mf67zaqpxweufe5wcf552",
			"moniker": "CroutonDigital",
			"website": "https://nodes.crouton.digital",
			"token": 4000000,
			"commission": 0.1,
			"votingPower": 0,
			"rank": 100,
			"jailed": false,
			"participation": 0.0,
			"windowMissCount": 90.6,
			"commissionScore": 50.0,
			"totalScore": 46.86666666666667,
			"level": 2
		},
		{
			"address": "bandvaloper1m3fdqwp27vq3jncjtvrd5vqn74femut6kfsd0z",
			"moniker": "testvalidator",
			"website": "",
			"token": 3999600,
			"commission": 0.1,
			"votingPower": 0,
			"rank": 101,
			"jailed": true,
			"windowMissCount": 50,
			"commissionScore": 50.0,
			"totalScore": 33.333333333333336,
			"level": 2
		},
		{
			"address": "bandvaloper1sh7u6c0g2s5ysg6c69pywnn55jx5wel7cstm7s",
			"moniker": "TheBestNode",
			"website": "",
			"token": 3899400,
			"commission": 0.05,
			"votingPower": 0,
			"rank": 101,
			"jailed": true,
			"windowMissCount": 50,
			"commissionScore": 25.0,
			"totalScore": 25.0,
			"level": 1
		},
		{
			"address": "bandvaloper1vgncrw4pxyqmgj0tm2t7hv4sr0sez3774szv36",
			"moniker": "dwentz.lol",
			"website": "https://dwentz.lol",
			"token": 3593635,
			"commission": 0.01,
			"votingPower": 0,
			"rank": 101,
			"jailed": true,
			"windowMissCount": 50,
			"commissionScore": 5.0,
			"totalScore": 18.333333333333332,
			"level": 1
		},
		{
			"address": "bandvaloper1u6439zrwzrk7p943v0gtzmkewwg9yrthju9dra",
			"moniker": "BlockSensus",
			"website": "www.blocksensus.io",
			"token": 3199753,
			"commission": 0.1,
			"votingPower": 0,
			"rank": 101,
			"jailed": true,
			"windowMissCount": 50,
			"commissionScore": 50.0,
			"totalScore": 33.333333333333336,
			"level": 2
		},
		{
			"address": "bandvaloper1a2gppugantns8zad44dpdwew2dln4kfzkajgk4",
			"moniker": "0% Fee to 2023 | Avaulto.com",
			"website": "Avaulto.com",
			"token": 3012992,
			"commission": 0,
			"votingPower": 0,
			"rank": 101,
			"jailed": true,
			"windowMissCount": 50,
			"commissionScore": 0,
			"totalScore": 16.666666666666668,
			"level": 1
		},
		{
			"address": "bandvaloper13trvxrt2ua7k7q80hgxspqvq9zecz86dpc8fqn",
			"moniker": "masternode",
			"website": "",
			"token": 2999700,
			"commission": 0.1,
			"votingPower": 0,
			"rank": 101,
			"jailed": true,
			"windowMissCount": 50,
			"commissionScore": 50.0,
			"totalScore": 33.333333333333336,
			"level": 2
		},
		{
			"address": "bandvaloper1wxqdw43g8sz9vxfhmnrc7shsy9r3lq2782knl2",
			"moniker": "NilniaBand",
			"website": "https://nilnia.io",
			"token": 2999700,
			"commission": 0.05,
			"votingPower": 0,
			"rank": 101,
			"jailed": true,
			"windowMissCount": 50,
			"commissionScore": 25.0,
			"totalScore": 25.0,
			"level": 1
		},
		{
			"address": "bandvaloper1k8szgnmljy0kd90wmv4rrp7mqx6zw9vxdknk4x",
			"moniker": "Validator.run | 100% Slash Protected",
			"website": "https://www.validator.run",
			"token": 2999700,
			"commission": 0.05,
			"votingPower": 0,
			"rank": 101,
			"jailed": true,
			"windowMissCount": 50,
			"commissionScore": 25.0,
			"totalScore": 25.0,
			"level": 1
		},
		{
			"address": "bandvaloper1datx5lw9nsys67er535xwrdky96mttt54vsk6v",
			"moniker": "JJack",
			"website": "",
			"token": 2999700,
			"commission": 0.1,
			"votingPower": 0,
			"rank": 101,
			"jailed": true,
			"windowMissCount": 50,
			"commissionScore": 50.0,
			"totalScore": 33.333333333333336,
			"level": 2
		},
		{
			"address": "bandvaloper17qe0qs34zp9rtxdc6an58rl0ys24g8wu5krr6d",
			"moniker": "RootsterLabs",
			"website": "",
			"token": 2999700,
			"commission": 0.1,
			"votingPower": 0,
			"rank": 101,
			"jailed": true,
			"windowMissCount": 50,
			"commissionScore": 50.0,
			"totalScore": 33.333333333333336,
			"level": 2
		},
		{
			"address": "bandvaloper1p7s39hake3mujfh4arees94zt9zdwfzpuzmjnj",
			"moniker": "0% fee | Avaulto.com",
			"website": "Avaulto.com",
			"token": 2999700,
			"commission": 0,
			"votingPower": 0,
			"rank": 101,
			"jailed": true,
			"windowMissCount": 50,
			"commissionScore": 0,
			"totalScore": 16.666666666666668,
			"level": 1
		},
		{
			"address": "bandvaloper1val7t7e48tyxutjhg5ra4pd0485z0fs8q23g6e",
			"moniker": "QuantaTech",
			"website": "",
			"token": 2694299,
			"commission": 0.05,
			"votingPower": 0,
			"rank": 101,
			"jailed": true,
			"windowMissCount": 50,
			"commissionScore": 25.0,
			"totalScore": 25.0,
			"level": 1
		},
		{
			"address": "bandvaloper1gv2gnnqa5gs924mrenz2y4m5aadefwvgxq5nzr",
			"moniker": "Terraform Labs",
			"website": "https://terra.money/",
			"token": 2177211,
			"commission": 0.02,
			"votingPower": 0,
			"rank": 101,
			"jailed": true,
			"windowMissCount": 50,
			"commissionScore": 10.0,
			"totalScore": 20.0,
			"level": 1
		},
		{
			"address": "bandvaloper1aw58v3l9yrk262fjr9ah0c0a39xf9hwr4yw04u",
			"moniker": "stake9",
			"website": "",
			"token": 2156692,
			"commission": 0.05,
			"votingPower": 0,
			"rank": 101,
			"jailed": true,
			"windowMissCount": 50,
			"commissionScore": 25.0,
			"totalScore": 25.0,
			"level": 1
		},
		{
			"address": "bandvaloper1yhj9uqacyjrqyt58d548ywayhw52ff524tw3gh",
			"moniker": "NQ4.NET",
			"website": "https://nq4.net",
			"token": 2019799,
			"commission": 0.09,
			"votingPower": 0,
			"rank": 101,
			"jailed": true,
			"windowMissCount": 50,
			"commissionScore": 44.99999999999999,
			"totalScore": 31.666666666666668,
			"level": 2
		},
		{
			"address": "bandvaloper19ang3d293gsqe64wakp7t0h5s4crrxr7vp7trm",
			"moniker": "NodeX Emperor \u26a1 BandChain",
			"website": "https://nodex.one",
			"token": 2000000,
			"commission": 0.01,
			"votingPower": 0,
			"rank": 101,
			"jailed": false,
			"participation": 0.0,
			"windowMissCount": 91.7,
			"commissionScore": 5.0,
			"totalScore": 32.233333333333334,
			"level": 2
		},
		{
			"address": "bandvaloper1ufjqrau2w0vjd84e5sp86lcvyn4ktqdet9mgs5",
			"moniker": "\ud83d\uddfcStableNode\ud83d\uddfc",
			"website": "",
			"token": 2000000,
			"commission": 0.05,
			"votingPower": 0,
			"rank": 101,
			"jailed": true,
			"windowMissCount": 50,
			"commissionScore": 25.0,
			"totalScore": 25.0,
			"level": 1
		},
		{
			"address": "bandvaloper145a0pq4v3dqhfgpvwtkt425arxydhz3ql7cn95",
			"moniker": "Indonode",
			"website": "https://indonode.net/",
			"token": 1999800,
			"commission": 0.01,
			"votingPower": 0,
			"rank": 101,
			"jailed": false,
			"windowMissCount": 50,
			"commissionScore": 5.0,
			"totalScore": 18.333333333333332,
			"level": 1
		},
		{
			"address": "bandvaloper1d7ul50ewkddfz8cd43695vggvrdmmq2nxuh5w5",
			"moniker": "MapleSyrup",
			"website": "https://maplesyrup-node.xyz",
			"token": 1999800,
			"commission": 0.1,
			"votingPower": 0,
			"rank": 101,
			"jailed": true,
			"windowMissCount": 50,
			"commissionScore": 50.0,
			"totalScore": 33.333333333333336,
			"level": 2
		},
		{
			"address": "bandvaloper179ua384fgncu4vnxr0phkks9f3tmwh7u37jfsp",
			"moniker": "blockpower",
			"website": "",
			"token": 1924998,
			"commission": 0.1,
			"votingPower": 0,
			"rank": 101,
			"jailed": true,
			"windowMissCount": 50,
			"commissionScore": 50.0,
			"totalScore": 33.333333333333336,
			"level": 2
		},
		{
			"address": "bandvaloper1t645rmmml583ekrupjstxwkkxtugv5laqekjyk",
			"moniker": "Aussie_Band",
			"website": "",
			"token": 1859587,
			"commission": 0.08,
			"votingPower": 0,
			"rank": 101,
			"jailed": true,
			"windowMissCount": 50,
			"commissionScore": 40.0,
			"totalScore": 30.0,
			"level": 2
		},
		{
			"address": "bandvaloper1n23u6ne8pezu4ugtu5tpztn9m28lr77g9ujff3",
			"moniker": "Finantra.com",
			"website": "",
			"token": 1499978,
			"commission": 0,
			"votingPower": 0,
			"rank": 101,
			"jailed": true,
			"windowMissCount": 50,
			"commissionScore": 0,
			"totalScore": 16.666666666666668,
			"level": 1
		},
		{
			"address": "bandvaloper1k68q3a9fwvke7pqc8tqftm6azddtd42f58px04",
			"moniker": "Cosmos Cats CLOSING redelegate please",
			"website": "",
			"token": 1209883,
			"commission": 0.05,
			"votingPower": 0,
			"rank": 101,
			"jailed": true,
			"windowMissCount": 50,
			"commissionScore": 25.0,
			"totalScore": 25.0,
			"level": 1
		},
		{
			"address": "bandvaloper1mehkk6whtfzrjevqj52a5gl5q5lfz5t0q9gl3y",
			"moniker": "Redelegate",
			"website": "",
			"token": 1149900,
			"commission": 0.05,
			"votingPower": 0,
			"rank": 101,
			"jailed": true,
			"windowMissCount": 50,
			"commissionScore": 25.0,
			"totalScore": 25.0,
			"level": 1
		},
		{
			"address": "bandvaloper1gqtkvth46l0c92gmss36xd4uexyvgah7nrm5wd",
			"moniker": "Huobipools",
			"website": "",
			"token": 1004772,
			"commission": 0.01,
			"votingPower": 0,
			"rank": 101,
			"jailed": true,
			"windowMissCount": 50,
			"commissionScore": 5.0,
			"totalScore": 18.333333333333332,
			"level": 1
		},
		{
			"address": "bandvaloper10daycr4xgqtwccqxmjgnnzhgmkvk8r9sk4kk7r",
			"moniker": "Castlenode",
			"website": "https://www.castlenode.com/",
			"token": 1000001,
			"commission": 0.1,
			"votingPower": 0,
			"rank": 101,
			"jailed": true,
			"windowMissCount": 50,
			"commissionScore": 50.0,
			"totalScore": 33.333333333333336,
			"level": 2
		},
		{
			"address": "bandvaloper1cdw85crdlwv9cq3plpfhm7m23kcmlx86eq4m77",
			"moniker": "TestnetPride",
			"website": "http://testnet-pride.com",
			"token": 1000000,
			"commission": 0.1,
			"votingPower": 0,
			"rank": 101,
			"jailed": false,
			"windowMissCount": 99.0,
			"commissionScore": 50.0,
			"totalScore": 49.666666666666664,
			"level": 2
		},
		{
			"address": "bandvaloper1thzsamfgurf5mq3d8q7mtjqlxrm3vljr5p7y7q",
			"moniker": "A-gaming",
			"website": "",
			"token": 999900,
			"commission": 0.1,
			"votingPower": 0,
			"rank": 101,
			"jailed": true,
			"windowMissCount": 50,
			"commissionScore": 50.0,
			"totalScore": 33.333333333333336,
			"level": 2
		},
		{
			"address": "bandvaloper1vfqhc5w8qspmlhrxxfjjknpujxlyw85su2ddva",
			"moniker": "NomadValidator",
			"website": "https://nomadvalidator.com",
			"token": 999900,
			"commission": 0.1,
			"votingPower": 0,
			"rank": 101,
			"jailed": true,
			"windowMissCount": 50,
			"commissionScore": 50.0,
			"totalScore": 33.333333333333336,
			"level": 2
		},
		{
			"address": "bandvaloper1l04xw3je6qxqzu238secztfjx6x40wrqwm96c7",
			"moniker": "metaONE",
			"website": "https://metaone.solutions",
			"token": 999900,
			"commission": 0.01,
			"votingPower": 0,
			"rank": 101,
			"jailed": true,
			"windowMissCount": 50,
			"commissionScore": 5.0,
			"totalScore": 18.333333333333332,
			"level": 1
		},
		{
			"address": "bandvaloper1at8hyqwek8uu6e24nw2ctj8c4thde83r5676cf",
			"moniker": "KiKi Finance",
			"website": "https://kiki.finance/",
			"token": 999900,
			"commission": 1,
			"votingPower": 0,
			"rank": 101,
			"jailed": true,
			"windowMissCount": 50,
			"commissionScore": 100,
			"totalScore": 50.0,
			"level": 3
		},
		{
			"address": "bandvaloper15cfelpcmukn9vgandsavvk3d5s43mkhcjdha9t",
			"moniker": "BitStack-0",
			"website": "https://bitstack.com",
			"token": 999900,
			"commission": 0.05,
			"votingPower": 0,
			"rank": 101,
			"jailed": false,
			"windowMissCount": 50,
			"commissionScore": 25.0,
			"totalScore": 25.0,
			"level": 1
		},
		{
			"address": "bandvaloper170umrcfkg87xmt2wqzjldpdzxgd2tj7ayeuqxp",
			"moniker": "band666",
			"website": "",
			"token": 999881,
			"commission": 0.1,
			"votingPower": 0,
			"rank": 101,
			"jailed": true,
			"windowMissCount": 50,
			"commissionScore": 50.0,
			"totalScore": 33.333333333333336,
			"level": 2
		},
		{
			"address": "bandvaloper15nzjxqpgmnv474l600ykynlmztkx9aaxjsg3l0",
			"moniker": "B1tStrata1",
			"website": "",
			"token": 960000,
			"commission": 0.1,
			"votingPower": 0,
			"rank": 101,
			"jailed": true,
			"windowMissCount": 50,
			"commissionScore": 50.0,
			"totalScore": 33.333333333333336,
			"level": 2
		},
		{
			"address": "bandvaloper196d8njsm29r592phdnlavpr7cf2cthu57sh73r",
			"moniker": "DO NOT STAKE",
			"website": "http://criticalstaking.com",
			"token": 737498,
			"commission": 0.08,
			"votingPower": 0,
			"rank": 101,
			"jailed": false,
			"windowMissCount": 50,
			"commissionScore": 40.0,
			"totalScore": 30.0,
			"level": 2
		},
		{
			"address": "bandvaloper15xu4q8l4qkld2wtej72z7gdx4r06raf8phnww3",
			"moniker": "NODELEGATE",
			"website": "",
			"token": 300303,
			"commission": 1,
			"votingPower": 0,
			"rank": 101,
			"jailed": true,
			"windowMissCount": 50,
			"commissionScore": 100,
			"totalScore": 50.0,
			"level": 3
		},
		{
			"address": "bandvaloper1xdasdrap3a0chue4mjs3as7d0x0ag5lmqrmvj7",
			"moniker": "deprecated",
			"website": "",
			"token": 296583,
			"commission": 0,
			"votingPower": 0,
			"rank": 101,
			"jailed": true,
			"windowMissCount": 50,
			"commissionScore": 0,
			"totalScore": 16.666666666666668,
			"level": 1
		},
		{
			"address": "bandvaloper15eqaawst9s9lvxs90m9fj2ly99m8pgy3jp9yp7",
			"moniker": "deprecated",
			"website": "",
			"token": 109891,
			"commission": 0.08,
			"votingPower": 0,
			"rank": 101,
			"jailed": false,
			"windowMissCount": 50,
			"commissionScore": 40.0,
			"totalScore": 30.0,
			"level": 2
		},
		{
			"address": "bandvaloper195k4eh3ng9wa5k2r7s4p2yz2tjkwpkjp972pfk",
			"moniker": "block42",
			"website": "https://block42.com",
			"token": 104043,
			"commission": 0.2,
			"votingPower": 0,
			"rank": 101,
			"jailed": true,
			"windowMissCount": 50,
			"commissionScore": 100.0,
			"totalScore": 50.0,
			"level": 3
		},
		{
			"address": "bandvaloper1zyc9ptapecmxtlnfe20kyq2cgncsedee2rv8up",
			"moniker": "kooltek68",
			"website": "https://twitter.com/HungNgu76442123",
			"token": 96497,
			"commission": 0.04,
			"votingPower": 0,
			"rank": 101,
			"jailed": false,
			"windowMissCount": 50,
			"commissionScore": 20.0,
			"totalScore": 23.333333333333332,
			"level": 1
		},
		{
			"address": "bandvaloper14xgc4kpr7kqm0rtdzu67hg6ajjx7mmzr4eawae",
			"moniker": "DO NOT DELEGATE",
			"website": "",
			"token": 92032,
			"commission": 0.01,
			"votingPower": 0,
			"rank": 101,
			"jailed": true,
			"windowMissCount": 50,
			"commissionScore": 5.0,
			"totalScore": 18.333333333333332,
			"level": 1
		},
		{
			"address": "bandvaloper16xw6g374x57j5adp95e09pdeen5w6tfaaz5l7u",
			"moniker": "Closing - Please redelegate",
			"website": "https://matters.news/@oldcat",
			"token": 22001,
			"commission": 0,
			"votingPower": 0,
			"rank": 101,
			"jailed": true,
			"windowMissCount": 50,
			"commissionScore": 0,
			"totalScore": 16.666666666666668,
			"level": 1
		},
		{
			"address": "bandvaloper18kwcnkpy9qyp8tswvlchwp8x7c5uauznukec6l",
			"moniker": "band-val-01.appauto.ca",
			"website": "",
			"token": 9959,
			"commission": 0.05,
			"votingPower": 0,
			"rank": 101,
			"jailed": false,
			"windowMissCount": 50,
			"commissionScore": 25.0,
			"totalScore": 25.0,
			"level": 1
		},
		{
			"address": "bandvaloper120u947tfjqhal8gx4qqd7xdafp3raaqfw6nmkt",
			"moniker": "decomissioned",
			"website": "",
			"token": 7701,
			"commission": 0.08,
			"votingPower": 0,
			"rank": 101,
			"jailed": false,
			"windowMissCount": 50,
			"commissionScore": 40.0,
			"totalScore": 30.0,
			"level": 2
		},
		{
			"address": "bandvaloper1rn7je95tnfjmkdrkvjeu42ayq4e5wa69dljpjj",
			"moniker": "Farewell",
			"website": "",
			"token": 6000,
			"commission": 0.1,
			"votingPower": 0,
			"rank": 101,
			"jailed": false,
			"windowMissCount": 50,
			"commissionScore": 50.0,
			"totalScore": 33.333333333333336,
			"level": 2
		},
		{
			"address": "bandvaloper1kek6uj3ux6f8k6mq0pewh5s7v7m0empy6zymyf",
			"moniker": "[Please_re-delegate_to_another_node]",
			"website": "http://",
			"token": 5000,
			"commission": 0.11,
			"votingPower": 0,
			"rank": 101,
			"jailed": true,
			"windowMissCount": 50,
			"commissionScore": 54.99999999999999,
			"totalScore": 35.0,
			"level": 2
		},
		{
			"address": "bandvaloper1s48t7zq4akptya09axuxem8hntyy93gu28fp50",
			"moniker": "ThePassiveTrust",
			"website": "",
			"token": 4866,
			"commission": 0.1,
			"votingPower": 0,
			"rank": 101,
			"jailed": true,
			"windowMissCount": 50,
			"commissionScore": 50.0,
			"totalScore": 33.333333333333336,
			"level": 2
		},
		{
			"address": "bandvaloper1xwgyl7dx7p68uxhl75m7rdr06jcvjpzsmcsfx8",
			"moniker": "Atlas Staking (-- Auto compound rewards --)",
			"website": "www.atlas-staking.com/staking-band/",
			"token": 955,
			"commission": 0.05,
			"votingPower": 0,
			"rank": 101,
			"jailed": true,
			"windowMissCount": 50,
			"commissionScore": 25.0,
			"totalScore": 25.0,
			"level": 1
		},
		{
			"address": "bandvaloper136acr6ytwcmavxwqwj8nxnjqka7xrle0ck3tkj",
			"moniker": "NoDelegate",
			"website": " ",
			"token": 415,
			"commission": 0.12,
			"votingPower": 0,
			"rank": 101,
			"jailed": true,
			"windowMissCount": 50,
			"commissionScore": 60.0,
			"totalScore": 36.666666666666664,
			"level": 2
		},
		{
			"address": "bandvaloper1875xujunckez0grudl8qml7r69e3qwe5x3pt5r",
			"moniker": "DO NOT DELEGATE - Pompey",
			"website": "",
			"token": 402,
			"commission": 0.1,
			"votingPower": 0,
			"rank": 101,
			"jailed": true,
			"windowMissCount": 50,
			"commissionScore": 50.0,
			"totalScore": 33.333333333333336,
			"level": 2
		},
		{
			"address": "bandvaloper14jlwymm640f2erv3dsnv0suhey4g98p3072gp5",
			"moniker": "SeaX Ventures II",
			"website": "",
			"token": 76,
			"commission": 0.06,
			"votingPower": 0,
			"rank": 101,
			"jailed": true,
			"windowMissCount": 50,
			"commissionScore": 30.0,
			"totalScore": 26.666666666666668,
			"level": 1
		},
		{
			"address": "bandvaloper1uj0v9gcc9u340c3h0uw6lm05qewk2w729l2qj8",
			"moniker": "frsmallhope",
			"website": "",
			"token": 47,
			"commission": 0.1,
			"votingPower": 0,
			"rank": 101,
			"jailed": false,
			"windowMissCount": 50,
			"commissionScore": 50.0,
			"totalScore": 33.333333333333336,
			"level": 2
		},
		{
			"address": "bandvaloper1j7vxavm0q66w5t04wv8zxlv09t70hd72n35w7n",
			"moniker": "SeaX Ventures III",
			"website": "http://seax.vc/",
			"token": 9,
			"commission": 0.06,
			"votingPower": 0,
			"rank": 101,
			"jailed": true,
			"windowMissCount": 50,
			"commissionScore": 30.0,
			"totalScore": 26.666666666666668,
			"level": 1
		},
		{
			"address": "bandvaloper1ya8zqwdrm6fm49czexlh3fz5y84nly4vn9uqp6",
			"moniker": "RubberBAND",
			"website": "",
			"token": 6,
			"commission": 0.09,
			"votingPower": 0,
			"rank": 101,
			"jailed": false,
			"windowMissCount": 50,
			"commissionScore": 44.99999999999999,
			"totalScore": 31.666666666666668,
			"level": 2
		},
		{
			"address": "bandvaloper1ef2ak3ddypn9rh6qv7pxsywsp93wj755lye60t",
			"moniker": "AUXBOURG",
			"website": "",
			"token": 5,
			"commission": 0.1,
			"votingPower": 0,
			"rank": 101,
			"jailed": false,
			"windowMissCount": 50,
			"commissionScore": 50.0,
			"totalScore": 33.333333333333336,
			"level": 2
		},
		{
			"address": "bandvaloper13n9sssaq9a5kw37sg6emx4pl5jrpnwjjrrzh7g",
			"moniker": "Nosce",
			"website": "",
			"token": 4,
			"commission": 0.07,
			"votingPower": 0,
			"rank": 101,
			"jailed": true,
			"windowMissCount": 50,
			"commissionScore": 35.0,
			"totalScore": 28.333333333333332,
			"level": 1
		},
		{
			"address": "bandvaloper1fn75cg7fdv9yv3trvtmcxshagevu0pkydazwet",
			"moniker": "tradebit",
			"website": "https://band.tradebit.ca",
			"token": 3,
			"commission": 0.07,
			"votingPower": 0,
			"rank": 101,
			"jailed": true,
			"windowMissCount": 50,
			"commissionScore": 35.0,
			"totalScore": 28.333333333333332,
			"level": 1
		},
		{
			"address": "bandvaloper1ud4ux0q5v4gn3aak4mhq7ludsk946mj2c76e78",
			"moniker": "Haocomm Staking",
			"website": "https://www.haocomm-staking.com",
			"token": 2,
			"commission": 0.08,
			"votingPower": 0,
			"rank": 101,
			"jailed": true,
			"windowMissCount": 50,
			"commissionScore": 40.0,
			"totalScore": 30.0,
			"level": 2
		},
		{
			"address": "bandvaloper1q760jpzlak4kfr2t6udghwnp8puh3nxk3ef03x",
			"moniker": "GreenStake One",
			"website": "https://greenstake.one",
			"token": 2,
			"commission": 0.03,
			"votingPower": 0,
			"rank": 101,
			"jailed": true,
			"windowMissCount": 50,
			"commissionScore": 15.0,
			"totalScore": 21.666666666666668,
			"level": 1
		},
		{
			"address": "bandvaloper1rzg6t4j6sckxl0lg9rpyhp3j6mwtff8hdjrs6n",
			"moniker": "Blockpower_new",
			"website": "",
			"token": 1,
			"commission": 0.1,
			"votingPower": 0,
			"rank": 101,
			"jailed": true,
			"windowMissCount": 50,
			"commissionScore": 50.0,
			"totalScore": 33.333333333333336,
			"level": 2
		},
		{
			"address": "bandvaloper1k0l9rp8mz0sllw059gdt6vf7a60f8wj7tse7gm",
			"moniker": "RETIRED",
			"website": "",
			"token": 0,
			"commission": 0.1,
			"votingPower": 0,
			"rank": 101,
			"jailed": true,
			"windowMissCount": 50,
			"commissionScore": 50.0,
			"totalScore": 33.333333333333336,
			"level": 2
		},
		{
			"address": "bandvaloper1cxamfvt9r37hjfr3h33r974p2a2h0ccklfczsr",
			"moniker": "ClosedPool",
			"website": "",
			"token": 0,
			"commission": 0.05,
			"votingPower": 0,
			"rank": 101,
			"jailed": true,
			"windowMissCount": 50,
			"commissionScore": 25.0,
			"totalScore": 25.0,
			"level": 1
		},
		{
			"address": "bandvaloper12es54qm7ldfetvknfgcg8qtxk3rt9lsmz4nz7w",
			"moniker": "Artemis One",
			"website": "https://artemisone.org",
			"token": 0,
			"commission": 0,
			"votingPower": 0,
			"rank": 101,
			"jailed": true,
			"windowMissCount": 50,
			"commissionScore": 0,
			"totalScore": 16.666666666666668,
			"level": 1
		},
		{
			"address": "bandvaloper1u9ulrehssfrjkvddpsqjq34slxsgz0d6gsge8a",
			"moniker": "Crypto Compass",
			"website": "",
			"token": 0,
			"commission": 0.03,
			"votingPower": 0,
			"rank": 101,
			"jailed": true,
			"windowMissCount": 50,
			"commissionScore": 15.0,
			"totalScore": 21.666666666666668,
			"level": 1
		},
		{
			"address": "bandvaloper1ql2swdtzyf5zmlzanqw0hgvdf8jd0t38ajp8jf",
			"moniker": "CoinBevy",
			"website": "https://coinbevy.com",
			"token": 0,
			"commission": 0.03,
			"votingPower": 0,
			"rank": 101,
			"jailed": true,
			"windowMissCount": 50,
			"commissionScore": 15.0,
			"totalScore": 21.666666666666668,
			"level": 1
		},
		{
			"address": "bandvaloper1vjnmadz7za0n2a6w58w8af2gmd0f23vkqvh6vd",
			"moniker": "cryptotiger",
			"website": "",
			"token": 0,
			"commission": 0.1,
			"votingPower": 0,
			"rank": 101,
			"jailed": true,
			"windowMissCount": 50,
			"commissionScore": 50.0,
			"totalScore": 33.333333333333336,
			"level": 2
		},
		{
			"address": "bandvaloper1m0hzvcc20nfcpa87ds3qutcnpemrawquq8ljg5",
			"moniker": "BiTurbo Capital \ud83d\udc8e",
			"website": "",
			"token": 0,
			"commission": 0.05,
			"votingPower": 0,
			"rank": 101,
			"jailed": true,
			"windowMissCount": 50,
			"commissionScore": 25.0,
			"totalScore": 25.0,
			"level": 1
		},
		{
			"address": "bandvaloper15zzk2f2md2w0rkrgrm6476qjwjj73dckzq8xp6",
			"moniker": "Share Staker",
			"website": "",
			"token": 0,
			"commission": 0.1,
			"votingPower": 0,
			"rank": 101,
			"jailed": true,
			"windowMissCount": 50,
			"commissionScore": 50.0,
			"totalScore": 33.333333333333336,
			"level": 2
		},
		{
			"address": "bandvaloper1u4xqjva2syju4z92pwjulr6s7srh35wpsmwm0l",
			"moniker": "Share Staker",
			"website": "",
			"token": 0,
			"commission": 0.1,
			"votingPower": 0,
			"rank": 101,
			"jailed": true,
			"windowMissCount": 50,
			"commissionScore": 50.0,
			"totalScore": 33.333333333333336,
			"level": 2
		},
		{
			"address": "bandvaloper19xdhqssgzp9xucgwns6ut2q5jxq60nu4eqqqfs",
			"moniker": "MKV.one",
			"website": "https://mkv.one",
			"token": 0,
			"commission": 0,
			"votingPower": 0,
			"rank": 101,
			"jailed": true,
			"windowMissCount": 50,
			"commissionScore": 0,
			"totalScore": 16.666666666666668,
			"level": 1
		},
		{
			"address": "bandvaloper1060qnrsu8p0atrxk4043papkhemkzsrl494fq7",
			"moniker": "adanode",
			"website": "adanode.me",
			"token": 0,
			"commission": 0.1,
			"votingPower": 0,
			"rank": 101,
			"jailed": true,
			"windowMissCount": 50,
			"commissionScore": 50.0,
			"totalScore": 33.333333333333336,
			"level": 2
		}
	]
}
